


<PubmedArticle>
    <MedlineCitation Status="In-Data-Review" Owner="NLM">
        <PMID Version="1">31199910</PMID>
        <DateRevised>
            <Year>2019</Year>
            <Month>06</Month>
            <Day>14</Day>
        </DateRevised>
        <Article PubModel="Print">
            <Journal>
                <ISSN IssnType="Electronic">1097-4172</ISSN>
                <JournalIssue CitedMedium="Internet">
                    <Volume>177</Volume>
                    <Issue>7</Issue>
                    <PubDate>
                        <Year>2019</Year>
                        <Month>Jun</Month>
                        <Day>13</Day>
                    </PubDate>
                </JournalIssue>
                <Title>Cell</Title>
                <ISOAbbreviation>Cell</ISOAbbreviation>
            </Journal>
            <ArticleTitle>Could iPSCs Enable &quot;Off-the-Shelf&quot; Cell Therapy?</ArticleTitle>
            <Pagination>
                <MedlinePgn>1667-1669</MedlinePgn>
            </Pagination>
            <ELocationID EIdType="pii" ValidYN="Y">S0092-8674(19)30614-2</ELocationID>
            <ELocationID EIdType="doi" ValidYN="Y">10.1016/j.cell.2019.05.043</ELocationID>
            <Abstract>
                <AbstractText>An &quot;off-the-shelf&quot; cell therapy derived from induced pluripotent stem cells (iPSCs) has entered clinical trials in the United States. Other companies are following suit, harnessing iPSCs' self-renewal ability to manufacture cell therapies that don't require customization for each patient. But some experts aren't sure such therapies are a good idea.</AbstractText>
                <CopyrightInformation>Copyright © 2019 Elsevier Inc. All rights reserved.</CopyrightInformation>
            </Abstract>
            <AuthorList CompleteYN="Y">
                <Author ValidYN="Y">
                    <LastName>Crow</LastName>
                    <ForeName>Diana</ForeName>
                    <Initials>D</Initials>
                    <AffiliationInfo>
                        <Affiliation>Cambridge, MA, USA.</Affiliation>
                    </AffiliationInfo>
                </Author>
            </AuthorList>
            <Language>eng</Language>
            <PublicationTypeList>
                <PublicationType UI="D016428">Journal Article</PublicationType>
            </PublicationTypeList>
        </Article>
        <MedlineJournalInfo>
            <Country>United States</Country>
            <MedlineTA>Cell</MedlineTA>
            <NlmUniqueID>0413066</NlmUniqueID>
            <ISSNLinking>0092-8674</ISSNLinking>
        </MedlineJournalInfo>
    </MedlineCitation>
    <PubmedData>
        <History>
            <PubMedPubDate PubStatus="entrez">
                <Year>2019</Year>
                <Month>6</Month>
                <Day>15</Day>
                <Hour>6</Hour>
                <Minute>0</Minute>
            </PubMedPubDate>
            <PubMedPubDate PubStatus="pubmed">
                <Year>2019</Year>
                <Month>6</Month>
                <Day>15</Day>
                <Hour>6</Hour>
                <Minute>0</Minute>
            </PubMedPubDate>
            <PubMedPubDate PubStatus="medline">
                <Year>2019</Year>
                <Month>6</Month>
                <Day>15</Day>
                <Hour>6</Hour>
                <Minute>0</Minute>
            </PubMedPubDate>
        </History>
        <PublicationStatus>ppublish</PublicationStatus>
        <ArticleIdList>
            <ArticleId IdType="pubmed">31199910</ArticleId>
            <ArticleId IdType="pii">S0092-8674(19)30614-2</ArticleId>
            <ArticleId IdType="doi">10.1016/j.cell.2019.05.043</ArticleId>
        </ArticleIdList>
    </PubmedData>
</PubmedArticle>

