


<PubmedArticle>
    <MedlineCitation Status="Publisher" Owner="NLM">
        <PMID Version="1">31199485</PMID>
        <DateRevised>
            <Year>2019</Year>
            <Month>06</Month>
            <Day>14</Day>
        </DateRevised>
        <Article PubModel="Print-Electronic">
            <Journal>
                <ISSN IssnType="Electronic">1460-2393</ISSN>
                <JournalIssue CitedMedium="Internet">
                    <PubDate>
                        <Year>2019</Year>
                        <Month>Jun</Month>
                        <Day>14</Day>
                    </PubDate>
                </JournalIssue>
                <Title>QJM : monthly journal of the Association of Physicians</Title>
                <ISOAbbreviation>QJM</ISOAbbreviation>
            </Journal>
            <ArticleTitle>Usability of donor corneas harvested from the deceased having septicaemia or malignancy.</ArticleTitle>
            <ELocationID EIdType="pii" ValidYN="Y">hcz143</ELocationID>
            <ELocationID EIdType="doi" ValidYN="Y">10.1093/qjmed/hcz143</ELocationID>
            <Abstract>
                <AbstractText Label="CONTEXT" NlmCategory="BACKGROUND">There is a wide gap between supply and demand in relation to healthy corneal grafts. Specific contraindications like infection and malignancy lead to non-usage of many grafts, despite the fact that deeming graft unhealthyness for these two contraindications is debatable.</AbstractText>
                <AbstractText Label="AIMS" NlmCategory="OBJECTIVE">The present study was conceptualised to assess if corneas donated from the deceased with septicaemia or malignancy can be deemed fit for implantation.</AbstractText>
                <AbstractText Label="SETTINGS AND DESIGN" NlmCategory="METHODS">Retrospective histopathological and microbiological analysis of cadaveric donor corneas.</AbstractText>
                <AbstractText Label="METHODS AND MATERIAL" NlmCategory="METHODS">76 donor corneas from 38 patients rejected for corneal transplantation in view of patient having septicaemia or malignany were analysed for pathological and microbiological workup, to look for dissemination of disease within corneal tissue.Pathology workup included gross and microscopic histopathological evaluation of tissue.Microbiology workup included Grams stain and KOH with calcoflour mount, culture in blood agar, chocolate agar, Sabourauds dextrose agar and Mc Conkeys broth.</AbstractText>
                <AbstractText Label="RESULTS" NlmCategory="RESULTS">46 donor corneas of 23 septicaemia patients when evaluated showed presence of culture positive infection in 18 patients (78.2%).Histopathological examination done for 30 donor corneas from 15 cancer patients did not reveal presence of tumour cells in the specimen. Corneas of 2 of cancer patients having septicaemia revealed growth on cultures.</AbstractText>
                <AbstractText Label="CONCLUSIONS" NlmCategory="CONCLUSIONS">Corneal tissues harvested from septicaemia donors showed significantly higher incidence of corneal contamination, confirming their unsuitability for usageHowever, there was no incidence of tumour transmission in corneal tissues of the patients with malignancies, suggesting that they can be considered for ophthalmic purpose.</AbstractText>
                <CopyrightInformation>© The Author(s) 2019. Published by Oxford University Press on behalf of the Association of Physicians. All rights reserved. For Permissions, please email: journals.permissions@oup.com.</CopyrightInformation>
            </Abstract>
            <AuthorList CompleteYN="Y">
                <Author ValidYN="Y">
                    <LastName>Singh</LastName>
                    <ForeName>Tanu</ForeName>
                    <Initials>T</Initials>
                    <AffiliationInfo>
                        <Affiliation>Department of Ophthalmology, Government Medical College and Hospital, Chandigarh, India.</Affiliation>
                    </AffiliationInfo>
                </Author>
                <Author ValidYN="Y">
                    <LastName>Arya</LastName>
                    <ForeName>Sudesh Kumar</ForeName>
                    <Initials>SK</Initials>
                    <AffiliationInfo>
                        <Affiliation>Department of Ophthalmology, Government Medical College and Hospital, Chandigarh, India.</Affiliation>
                    </AffiliationInfo>
                </Author>
                <Author ValidYN="Y">
                    <LastName>Handa</LastName>
                    <ForeName>Uma</ForeName>
                    <Initials>U</Initials>
                    <AffiliationInfo>
                        <Affiliation>Department of Pathology, Government Medical College and Hospital, Chandigarh, India.</Affiliation>
                    </AffiliationInfo>
                </Author>
                <Author ValidYN="Y">
                    <LastName>Chander</LastName>
                    <ForeName>Jagdish</ForeName>
                    <Initials>J</Initials>
                    <AffiliationInfo>
                        <Affiliation>Department of Microbiology, Government Medical College and Hospital, Chandigarh, India.</Affiliation>
                    </AffiliationInfo>
                </Author>
            </AuthorList>
            <Language>eng</Language>
            <PublicationTypeList>
                <PublicationType UI="D016428">Journal Article</PublicationType>
            </PublicationTypeList>
            <ArticleDate DateType="Electronic">
                <Year>2019</Year>
                <Month>06</Month>
                <Day>14</Day>
            </ArticleDate>
        </Article>
        <MedlineJournalInfo>
            <Country>England</Country>
            <MedlineTA>QJM</MedlineTA>
            <NlmUniqueID>9438285</NlmUniqueID>
            <ISSNLinking>1460-2393</ISSNLinking>
        </MedlineJournalInfo>
        <KeywordList Owner="NOTNLM">
            <Keyword MajorTopicYN="N">cancer donor</Keyword>
            <Keyword MajorTopicYN="N">cancer transmission</Keyword>
            <Keyword MajorTopicYN="N">cornea donor selection</Keyword>
            <Keyword MajorTopicYN="N">corneal transplantation</Keyword>
            <Keyword MajorTopicYN="N">donor corneal contamination</Keyword>
            <Keyword MajorTopicYN="N">ocular metastasis</Keyword>
            <Keyword MajorTopicYN="N">septicaemia</Keyword>
        </KeywordList>
    </MedlineCitation>
    <PubmedData>
        <History>
            <PubMedPubDate PubStatus="received">
                <Year>2019</Year>
                <Month>05</Month>
                <Day>07</Day>
            </PubMedPubDate>
            <PubMedPubDate PubStatus="revised">
                <Year>2019</Year>
                <Month>05</Month>
                <Day>30</Day>
            </PubMedPubDate>
            <PubMedPubDate PubStatus="accepted">
                <Year>2019</Year>
                <Month>06</Month>
                <Day>03</Day>
            </PubMedPubDate>
            <PubMedPubDate PubStatus="entrez">
                <Year>2019</Year>
                <Month>6</Month>
                <Day>15</Day>
                <Hour>6</Hour>
                <Minute>0</Minute>
            </PubMedPubDate>
            <PubMedPubDate PubStatus="pubmed">
                <Year>2019</Year>
                <Month>6</Month>
                <Day>15</Day>
                <Hour>6</Hour>
                <Minute>0</Minute>
            </PubMedPubDate>
            <PubMedPubDate PubStatus="medline">
                <Year>2019</Year>
                <Month>6</Month>
                <Day>15</Day>
                <Hour>6</Hour>
                <Minute>0</Minute>
            </PubMedPubDate>
        </History>
        <PublicationStatus>aheadofprint</PublicationStatus>
        <ArticleIdList>
            <ArticleId IdType="pubmed">31199485</ArticleId>
            <ArticleId IdType="pii">5519127</ArticleId>
            <ArticleId IdType="doi">10.1093/qjmed/hcz143</ArticleId>
        </ArticleIdList>
    </PubmedData>
</PubmedArticle>

